{
    "dev": "anirbansumon",
    "channels": [
        {
            "name": "Espn Nba",
            "url": "https://cdn1.zohanayaan.com:1686/hls/espn2.m3u8?md5=CnmMKQDla6cBclOtuTG9dw&expires=1781392729",
            "referer": "https://executeandship.com/",
            "origin": "https://executeandship.com"
        },
        {
            "name": "Willow",
            "url": "https://oz1.player0003.com:7061/hls/willowala5.m3u8?md5=MuKFWNpyk57IIAR-hvDaJw&expires=1781392741&ch=willowala5&s=12a6814bc908b52c70023046b7216b8b",
            "referer": "https://player0003.com/",
            "origin": "https://executeandship.com"
        },
        {
            "name": "Premim Sports 1",
            "url": "https://cdn4.zohanayaan.com:1686/hls/premieruk.m3u8?md5=3Eu8iH1cRA7eF2CNKow_Gw&expires=1781392750",
            "referer": "https://executeandship.com/",
            "origin": "https://executeandship.com"
        },
        {
            "name": "Ten Sports",
            "url": "https://cdn2.zohanayaan.com:1686/hls/tenspk.m3u8?md5=73MjuOB5JN7wrdM5K46AXA&expires=1781392761",
            "referer": "https://executeandship.com/",
            "origin": "https://executeandship.com"
        },
        {
            "name": "T-sports",
            "url": "https://oz2.player0003.com:7060/hls/gtvbd.m3u8?md5=1BLxRWD4hXwYZs-Q5-9G4Q&expires=1781392773&ch=gtvbd&s=4b52d818083ed6f9452bbbd9f896b3c8",
            "referer": "https://player0003.com/",
            "origin": "https://executeandship.com"
        },
        {
            "name": "Lalega Sports",
            "url": "https://cdn8.zohanayaan.com:1686/hls/laligatvhyper1.m3u8?md5=fav6buREJpTTuI4wn4Z0Zw&expires=1781392782",
            "referer": "https://executeandship.com/",
            "origin": "https://executeandship.com"
        },
        {
            "name": "TNT Sports",
            "url": "https://cdn10.zohanayaan.com:1686/hls/hdchnl2.m3u8?md5=6jsFzPiUv66Xtvtbs3-iFg&expires=1781392790",
            "referer": "https://executeandship.com/",
            "origin": "https://executeandship.com"
        },
        {
            "name": "Asian Sports Cricket",
            "url": "https://dz5.bhalocast.pro:7059/hls/asportspk.m3u8?md5=8zI_cP7gN5uFF8_vzr_jOA&expires=1781392803&ch=asportspk&s=74bd01364e3b9fb692fca550cf27ba06",
            "referer": "https://bhalocast.pro/",
            "origin": "https://executeandship.com"
        },
        {
            "name": "Tudn Sports",
            "url": "https://cdn3.zohanayaan.com:1686/hls/tudnusas.m3u8?md5=wP6FwXCWGIgx1Z-sPIhbNQ&expires=1781392812",
            "referer": "https://executeandship.com/",
            "origin": "https://executeandship.com"
        },
        {
            "name": "PTV Sports",
            "url": "https://cdn6.zohanayaan.com:1686/hls/ptvpk.m3u8?md5=PvJc3cvgOGi2FQ1h2pThTA&expires=1781392795",
            "referer": "https://executeandship.com/",
            "origin": "https://executeandship.com"
        },
        {
            "name": "Sky Sports Football",
            "url": "https://cdn7.zohanayaan.com:1686/hls/skysfott.m3u8?md5=2DHeONfYnsGCJmdL7ymAZg&expires=1781392831",
            "referer": "https://executeandship.com/",
            "origin": "https://executeandship.com"
        },
        {
            "name": "ESPN Deportes",
            "url": "https://cdn4.zohanayaan.com:1686/hls/espndeportess.m3u8?md5=ejxADr0d89H5lgeS_VcNeg&expires=1781392817",
            "referer": "https://executeandship.com/",
            "origin": "https://executeandship.com"
        },
        {
            "name": "Sky Sports 2",
            "url": "https://cdn9.zohanayaan.com:1686/hls/sky2nz.m3u8?md5=vI2wz6fZj7DjEtorXisqmQ&expires=1781392849",
            "referer": "https://executeandship.com/",
            "origin": "https://executeandship.com"
        },
        {
            "name": "willow HD 2",
            "url": "https://cdn3.zohanayaan.com:1686/hls/willowextra.m3u8?md5=FahhsvVlMmMGmCGqwPKm7Q&expires=1781392847",
            "referer": "https://executeandship.com/",
            "origin": "https://executeandship.com"
        },
        {
            "name": "Sky Sports 5",
            "url": "https://cdn7.zohanayaan.com:1686/hls/sky5nz.m3u8?md5=QwtvXVKeuZG5HBPQSuaPcw&expires=1781392868",
            "referer": "https://executeandship.com/",
            "origin": "https://executeandship.com"
        },
        {
            "name": "Sky Sports Action",
            "url": "https://cdn10.zohanayaan.com:1686/hls/skysact.m3u8?md5=bbIEUWo8A2VCwrP5cWzNTQ&expires=1781392879",
            "referer": "https://executeandship.com/",
            "origin": "https://executeandship.com"
        },
        {
            "name": "Ten Sports",
            "url": "https://cdn1.zohanayaan.com:1686/hls/tenspk.m3u8?md5=DD7ZzGgo0XNSBuj3AHRIPA&expires=1781392888",
            "referer": "https://executeandship.com/",
            "origin": "https://executeandship.com"
        },
        {
            "name": "Star Sports 2",
            "url": "https://oz1.player0003.com:7061/hls/star2cl5.m3u8?md5=Q3q_FjALd68IeVXSBBY2ug&expires=1781392899&ch=star2cl5&s=a29ac1bbbb8b7f7d730dcab2044ff4d2",
            "referer": "https://player0003.com/",
            "origin": "https://executeandship.com"
        },
        {
            "name": "Sky Sports 7",
            "url": "https://cdn2.zohanayaan.com:1686/hls/sky7nz.m3u8?md5=GJWhWd0L17pfjA0RtWwMWQ&expires=1781392906",
            "referer": "https://executeandship.com/",
            "origin": "https://executeandship.com"
        },
        {
            "name": "Espn 1",
            "url": "https://cdn4.zohanayaan.com:1686/hls/espnusa.m3u8?md5=u25x51XhXgWDOQCkqiY9qw&expires=1781392914",
            "referer": "https://executeandship.com/",
            "origin": "https://executeandship.com"
        },
        {
            "name": "Sky Sports 6",
            "url": "https://cdn1.zohanayaan.com:1686/hls/sky6nz.m3u8?md5=VVDKaLmb221qBCi9fUNTFw&expires=1781392925",
            "referer": "https://executeandship.com/",
            "origin": "https://executeandship.com"
        },
        {
            "name": "Fox Sports 2",
            "url": "https://cdn7.zohanayaan.com:1686/hls/foxsp2usa.m3u8?md5=4WJa76aYmAt0E6pyNj7cuA&expires=1781392937",
            "referer": "https://executeandship.com/",
            "origin": "https://executeandship.com"
        },
        {
            "name": "Sky Sports 3",
            "url": "https://cdn2.zohanayaan.com:1686/hls/sky3nz.m3u8?md5=9A6j8yQ71W5W_-jE6kD4uQ&expires=1781392921",
            "referer": "https://executeandship.com/",
            "origin": "https://executeandship.com"
        },
        {
            "name": "willow HD",
            "url": "https://cdn9.zohanayaan.com:1686/hls/willowusa.m3u8?md5=yGFaFwG2418RBnb17Jdt5g&expires=1781392939",
            "referer": "https://executeandship.com/",
            "origin": "https://executeandship.com"
        },
        {
            "name": "lalega Sports",
            "url": "https://cdn7.zohanayaan.com:1686/hls/laligauk.m3u8?md5=wsUUSTMlFm8ggCViPpDYnw&expires=1781392959",
            "referer": "https://executeandship.com/",
            "origin": "https://executeandship.com"
        },
        {
            "name": "Telmunda Sports",
            "url": "https://cdn2.zohanayaan.com:1686/hls/telmunda.m3u8?md5=KZYjDxKfoWPGtL_UiuWgIQ&expires=1781392966",
            "referer": "https://executeandship.com/",
            "origin": "https://executeandship.com"
        },
        {
            "name": "Willow HD",
            "url": "https://dz5.bhalocast.pro:7059/hls/hdwillos5.m3u8?md5=xwsLx6pYaFKD1ItGYyLVnQ&expires=1781392992&ch=hdwillos5&s=a4ff6ac6fe6a41b87fc317ded2ef5d1c",
            "referer": "https://bhalocast.pro/",
            "origin": "https://executeandship.com"
        },
        {
            "name": "Fox Deportes",
            "url": "https://cdn9.zohanayaan.com:1686/hls/foxdeportesas1.m3u8?md5=XT493x6K3HScw4RtJaF6qw&expires=1781393000",
            "referer": "https://executeandship.com/",
            "origin": "https://executeandship.com"
        },
        {
            "name": "Fox Soccer Plus",
            "url": "https://cdn2.zohanayaan.com:1686/hls/foxsoccer.m3u8?md5=1pRBndqN6V2OuNTecCrCKg&expires=1781393003",
            "referer": "https://executeandship.com/",
            "origin": "https://executeandship.com"
        },
        {
            "name": "Star Sports 1 hindi",
            "url": "https://oz1.player0003.com:7061/hls/str1lhil5.m3u8?md5=QA0k3wrKfbi9SrKbfFPhlQ&expires=1781393020&ch=str1lhil5&s=0d6bb53c4689e936c5a0a990e8516cdf",
            "referer": "https://player0003.com/",
            "origin": "https://executeandship.com"
        },
        {
            "name": "Sky Sports laliga",
            "url": "https://cdn7.zohanayaan.com:1686/hls/sky8nz.m3u8?md5=SERB96QqRmJ_fhMOdyx7tw&expires=1781393030",
            "referer": "https://executeandship.com/",
            "origin": "https://executeandship.com"
        },
        {
            "name": "Sky Sports Cricket",
            "url": "https://dz5.bhalocast.pro:7059/hls/dodosky2.m3u8?md5=pf-PKnrjA86hD01oXCgQMA&expires=1781393042&ch=dodosky2&s=fdd1c5ee2ef4fe7f17a861ff48350c1a",
            "referer": "https://bhalocast.pro/",
            "origin": "https://executeandship.com"
        },
        {
            "name": "Mvemosa Sports",
            "url": "https://cdn6.zohanayaan.com:1686/hls/mvamoss.m3u8?md5=WD6gzIbmPhRQeSBGlO_X2A&expires=1781393051",
            "referer": "https://executeandship.com/",
            "origin": "https://executeandship.com"
        },
        {
            "name": "Sky Sports laliga 2",
            "url": "https://cdn6.zohanayaan.com:1686/hls/sky9nz.m3u8?md5=SXksFsRklxvju4p5NqH3AA&expires=1781393060",
            "referer": "https://executeandship.com/",
            "origin": "https://executeandship.com"
        },
        {
            "name": "Deportes ports",
            "url": "https://cdn10.zohanayaan.com:1686/hls/mdeportess.m3u8?md5=Kd9rsX4Zr04sDSSQ_OgeJg&expires=1781393070",
            "referer": "https://executeandship.com/",
            "origin": "https://executeandship.com"
        },
        {
            "name": "BBC News",
            "url": "https://cdn4.zohanayaan.com:1686/hls/hdchnl1.m3u8?md5=a5FPILp8icqP0_g6qO7jEA&expires=1781393055",
            "referer": "https://executeandship.com/",
            "origin": "https://executeandship.com"
        },
        {
            "name": "Fox Cricket",
            "url": "https://oz1.player0003.com:7061/hls/cf0sp1.m3u8?md5=X9XHa10iICwZw9kaCLo13A&expires=1781393102&ch=cf0sp1&s=50f85e1a18b4cf0f2b2fbbd698facea9",
            "referer": "https://player0003.com/",
            "origin": "https://executeandship.com"
        },
        {
            "name": "NBC Sports Now",
            "url": "https://cdn4.zohanayaan.com:1686/hls/nbccs.m3u8?md5=vW82-JDv94wb4d-beBZfFA&expires=1781393110",
            "referer": "https://executeandship.com/",
            "origin": "https://executeandship.com"
        },
        {
            "name": "TNT Sports 1",
            "url": "https://cdn9.zohanayaan.com:1686/hls/bbtsp1.m3u8?md5=mhjWqWiDpF82y_6skLpVeQ&expires=1781393118",
            "referer": "https://executeandship.com/",
            "origin": "https://executeandship.com"
        },
        {
            "name": "TNT Sports 2",
            "url": "https://cdn5.zohanayaan.com:1686/hls/bbtsp2.m3u8?md5=U41R2JgKpboJbGGsISj0aw&expires=1781393129",
            "referer": "https://executeandship.com/",
            "origin": "https://executeandship.com"
        },
        {
            "name": "A Sports",
            "url": "https://cdn2.zohanayaan.com:1686/hls/asportshd.m3u8?md5=Jh6w4DZN3AP34A9vEZ7Xzw&expires=1781393127",
            "referer": "https://executeandship.com/",
            "origin": "https://executeandship.com"
        },
        {
            "name": "Lalega Sports 2",
            "url": "https://cdn5.zohanayaan.com:1686/hls/laligatvhyper2.m3u8?md5=V1HcTnfXorjstog9M880Cw&expires=1781393146",
            "referer": "https://executeandship.com/",
            "origin": "https://executeandship.com"
        },
        {
            "name": "Ptv Sports Cricket",
            "url": "https://oz2.player0003.com:7060/hls/ptvskpr.m3u8?md5=ilWiC1g33x7VOGFc9heS7Q&expires=1781393156&ch=ptvskpr&s=f625977abc3ec32221946a78ffd9e2d5",
            "referer": "https://player0003.com/",
            "origin": "https://executeandship.com"
        },
        {
            "name": "bein Sports",
            "url": "https://cdn6.zohanayaan.com:1686/hls/beinusas.m3u8?md5=ZfWGe-qqefb5myx25ww_zA&expires=1781393163",
            "referer": "https://executeandship.com/",
            "origin": "https://executeandship.com"
        },
        {
            "name": "Sky Sports Tennis",
            "url": "https://cdn1.zohanayaan.com:1686/hls/skystennis.m3u8?md5=MamwODgtAAsqK7iMi4nhkg&expires=1781393171",
            "referer": "https://executeandship.com/",
            "origin": "https://executeandship.com"
        },
        {
            "name": "Sky Sports 4",
            "url": "https://cdn9.zohanayaan.com:1686/hls/sky4nz.m3u8?md5=8mm_iXhUEwpJ0cKzzt6KzQ&expires=1781393182",
            "referer": "https://executeandship.com/",
            "origin": "https://executeandship.com"
        },
        {
            "name": "Fox Sports 1",
            "url": "https://cdn6.zohanayaan.com:1686/hls/foxsp1usa.m3u8?md5=5uUgUxpIoxOp6P20pOhR2A&expires=1781393181",
            "referer": "https://executeandship.com/",
            "origin": "https://executeandship.com"
        },
        {
            "name": "Willow Extra",
            "url": "https://oz2.player0003.com:7060/hls/wextres5.m3u8?md5=rrZKJVYAazv4cQAYvmqaMw&expires=1781393202&ch=wextres5&s=97f0b1138a55539b153f1bf4b8b5acd9",
            "referer": "https://player0003.com/",
            "origin": "https://executeandship.com"
        },
        {
            "name": "Star Sports 1",
            "url": "https://oz2.player0003.com:7060/hls/star1kibich5.m3u8?md5=zpcksgfnqrtHMiLYvCITgg&expires=1781393214&ch=star1kibich5&s=ccadf76a9ba9e3b70cc966c54de816ea",
            "referer": "https://player0003.com/",
            "origin": "https://executeandship.com"
        }
    ]
}