{
    "dev": "anirbansumon",
    "channels": [
        {
            "name": "Lalega Sports 2",
            "url": "https://cdn3.zohanayaan.com:1686/hls/laligatvhyper2.m3u8?md5=qfheKBLHCHlcL8Xd4umQmg&expires=1781314612",
            "referer": "https://executeandship.com/",
            "origin": "https://executeandship.com"
        },
        {
            "name": "Sky Sports 4",
            "url": "https://cdn9.zohanayaan.com:1686/hls/sky4nz.m3u8?md5=hR8rxoTiSQJuhqBPRiBo6Q&expires=1781314623",
            "referer": "https://executeandship.com/",
            "origin": "https://executeandship.com"
        },
        {
            "name": "Sky Sports Football",
            "url": "https://cdn7.zohanayaan.com:1686/hls/skysfott.m3u8?md5=dBICeWK3jY7QBqXF4rODKw&expires=1781314635",
            "referer": "https://executeandship.com/",
            "origin": "https://executeandship.com"
        },
        {
            "name": "Lalega Sports",
            "url": "https://cdn1.zohanayaan.com:1686/hls/laligatvhyper1.m3u8?md5=AYx0uoXay5iFbNcAbpq4jw&expires=1781314644",
            "referer": "https://executeandship.com/",
            "origin": "https://executeandship.com"
        },
        {
            "name": "Sky Sports 3",
            "url": "https://cdn4.zohanayaan.com:1686/hls/sky3nz.m3u8?md5=xaLYy6P4bUlN_jSH1nlt6A&expires=1781314655",
            "referer": "https://executeandship.com/",
            "origin": "https://executeandship.com"
        },
        {
            "name": "Willow",
            "url": "https://oz2.player0003.com:7060/hls/willowala5.m3u8?md5=lETxGqoaZiyzlVEG6GTpcw&expires=1781314668&ch=willowala5&s=5c0ae75f89932a333151c51514d6d86a",
            "referer": "https://player0003.com/",
            "origin": "https://executeandship.com"
        },
        {
            "name": "Sky Sports Action",
            "url": "https://cdn8.zohanayaan.com:1686/hls/skysact.m3u8?md5=pGcIjylG1yWrlX5DD_gaQQ&expires=1781314678",
            "referer": "https://executeandship.com/",
            "origin": "https://executeandship.com"
        },
        {
            "name": "Sky Sports Cricket",
            "url": "https://dz5.bhalocast.pro:7059/hls/dodosky2.m3u8?md5=-pnKFzXihMZc-yvr3sPUMg&expires=1781314690&ch=dodosky2&s=dacdff0e81fee8e0efc6f9b9210059a9",
            "referer": "https://bhalocast.pro/",
            "origin": "https://executeandship.com"
        },
        {
            "name": "Sky Sports laliga",
            "url": "https://cdn10.zohanayaan.com:1686/hls/sky8nz.m3u8?md5=qXJtjyPq7RzW4BmKTje6fA&expires=1781314701",
            "referer": "https://executeandship.com/",
            "origin": "https://executeandship.com"
        },
        {
            "name": "Willow Extra",
            "url": "https://oz1.player0003.com:7061/hls/wextres5.m3u8?md5=gKGyxRjEM-3eik8IlCvNPg&expires=1781314711&ch=wextres5&s=89da8e681891214d05428de2ed3d85d9",
            "referer": "https://player0003.com/",
            "origin": "https://player0003.com"
        },
        {
            "name": "Ten Sports",
            "url": "https://cdn1.zohanayaan.com:1686/hls/tenspk.m3u8?md5=3v7GveZ7rEhwTYa9CxtW3w&expires=1781314705",
            "referer": "https://executeandship.com/",
            "origin": "https://executeandship.com"
        },
        {
            "name": "Star Sports 2",
            "url": "https://oz2.player0003.com:7060/hls/star2cl5.m3u8?md5=VMrrKfKrHypnk9ZWER4avw&expires=1781314732&ch=star2cl5&s=b5e03c1feb552c453c1449970da47db3",
            "referer": "https://player0003.com/",
            "origin": "https://executeandship.com"
        },
        {
            "name": "TNT Sports 2",
            "url": "https://cdn3.zohanayaan.com:1686/hls/bbtsp2.m3u8?md5=XWPZx8n7QgzW24kU28I8Nw&expires=1781314741",
            "referer": "https://executeandship.com/",
            "origin": "https://executeandship.com"
        },
        {
            "name": "willow HD 2",
            "url": "https://cdn5.zohanayaan.com:1686/hls/willowextra.m3u8?md5=G0CN7wt4gIizWOOqI83Eeg&expires=1781314751",
            "referer": "https://executeandship.com/",
            "origin": "https://executeandship.com"
        },
        {
            "name": "lalega Sports",
            "url": "https://cdn8.zohanayaan.com:1686/hls/laligauk.m3u8?md5=v8X0zqa4tChNLb9q73ARZg&expires=1781314763",
            "referer": "https://executeandship.com/",
            "origin": "https://executeandship.com"
        },
        {
            "name": "Mvemosa Sports",
            "url": "https://cdn3.zohanayaan.com:1686/hls/mvamoss.m3u8?md5=Z8NINo_CqjkJdkgJCIC49w&expires=1781314773",
            "referer": "https://executeandship.com/",
            "origin": "https://executeandship.com"
        },
        {
            "name": "Espn 1",
            "url": "https://cdn8.zohanayaan.com:1686/hls/espnusa.m3u8?md5=ybLXsqCXFXJXNhb8xP2L5A&expires=1781314782",
            "referer": "https://executeandship.com/",
            "origin": "https://executeandship.com"
        },
        {
            "name": "Asian Sports Cricket",
            "url": "https://dz5.bhalocast.pro:7059/hls/asportspk.m3u8?md5=P73AeYpPB0dXecGf8ju-6g&expires=1781314794&ch=asportspk&s=9a40e1063e103f07d1e3983656b39ad6",
            "referer": "https://bhalocast.pro/",
            "origin": "https://bhalocast.pro"
        },
        {
            "name": "Sky Sports 6",
            "url": "https://cdn4.zohanayaan.com:1686/hls/sky6nz.m3u8?md5=BqMqCQeoGJhGBte7vOXwmg&expires=1781314803",
            "referer": "https://executeandship.com/",
            "origin": "https://executeandship.com"
        },
        {
            "name": "Deportes ports",
            "url": "https://cdn6.zohanayaan.com:1686/hls/mdeportess.m3u8?md5=vPx2bjSyzp87nJZk0RANWA&expires=1781314803",
            "referer": "https://executeandship.com/",
            "origin": "https://executeandship.com"
        },
        {
            "name": "Tudn Sports",
            "url": "https://cdn5.zohanayaan.com:1686/hls/tudnusas.m3u8?md5=HYWEey5dY6KxGJMi73hGVg&expires=1781314808",
            "referer": "https://executeandship.com/",
            "origin": "https://executeandship.com"
        },
        {
            "name": "Sky Sports 5",
            "url": "https://cdn1.zohanayaan.com:1686/hls/sky5nz.m3u8?md5=smaH21fekxQzdX3WiIhh4g&expires=1781314807",
            "referer": "https://executeandship.com/",
            "origin": "https://executeandship.com"
        },
        {
            "name": "Star Sports 1 hindi",
            "url": "https://oz1.player0003.com:7061/hls/str1lhil5.m3u8?md5=Xs2UHh4HdWsuGxjMUMBSyQ&expires=1781314845&ch=str1lhil5&s=d40f54feec7b926b2ce2a6395037e8a9",
            "referer": "https://player0003.com/",
            "origin": "https://executeandship.com"
        },
        {
            "name": "Premim Sports 1",
            "url": "https://cdn7.zohanayaan.com:1686/hls/premieruk.m3u8?md5=wQQ4tnxJUZh-73NHVaADaQ&expires=1781314854",
            "referer": "https://executeandship.com/",
            "origin": "https://executeandship.com"
        },
        {
            "name": "Sky Sports laliga 2",
            "url": "https://cdn7.zohanayaan.com:1686/hls/sky9nz.m3u8?md5=Z8o_uSyr_WzXKBZmWO-nrw&expires=1781314863",
            "referer": "https://executeandship.com/",
            "origin": "https://executeandship.com"
        },
        {
            "name": "Sky Sports 7",
            "url": "https://cdn1.zohanayaan.com:1686/hls/sky7nz.m3u8?md5=8hSjELlr1a4xM4jKnT-nEg&expires=1781314873",
            "referer": "https://executeandship.com/",
            "origin": "https://executeandship.com"
        },
        {
            "name": "T-sports",
            "url": "https://oz2.player0003.com:7060/hls/gtvbd.m3u8?md5=c6XSQXelq_O4OKr8DRVTkg&expires=1781314883&ch=gtvbd&s=b357fcd6ca318823907a8aad158d3c49",
            "referer": "https://player0003.com/",
            "origin": "https://executeandship.com"
        },
        {
            "name": "PTV Sports",
            "url": "https://cdn8.zohanayaan.com:1686/hls/ptvpk.m3u8?md5=WMghVhy2Jj4ppyycNvZkbA&expires=1781314878",
            "referer": "https://executeandship.com/",
            "origin": "https://executeandship.com"
        },
        {
            "name": "Willow HD",
            "url": "https://dz5.bhalocast.pro:7059/hls/hdwillos5.m3u8?md5=LkGOGV0glULVnA9p43M-Yg&expires=1781314904&ch=hdwillos5&s=538804ca3d7fb9433abdd0540bdfe6ff",
            "referer": "https://bhalocast.pro/",
            "origin": "https://bhalocast.pro"
        },
        {
            "name": "bein Sports",
            "url": "https://cdn5.zohanayaan.com:1686/hls/beinusas.m3u8?md5=fhVLWrH04bU2JegSIy-V0w&expires=1781314913",
            "referer": "https://executeandship.com/",
            "origin": "https://executeandship.com"
        },
        {
            "name": "Telmunda Sports",
            "url": "https://cdn4.zohanayaan.com:1686/hls/telmunda.m3u8?md5=WN-WIVptFy6zSYnKg1Is4w&expires=1781314910",
            "referer": "https://executeandship.com/",
            "origin": "https://executeandship.com"
        },
        {
            "name": "Fox Soccer Plus",
            "url": "https://cdn6.zohanayaan.com:1686/hls/foxsoccer.m3u8?md5=ZASSk3d8r4CxQl10nqhN9w&expires=1781314932",
            "referer": "https://executeandship.com/",
            "origin": "https://executeandship.com"
        },
        {
            "name": "Fox Cricket",
            "url": "https://oz1.player0003.com:7061/hls/cf0sp1.m3u8?md5=36U3NzoDdODLMuYttf6dUw&expires=1781314942&ch=cf0sp1&s=a9249122caf0dd7cccb17ddb7b7991e2",
            "referer": "https://player0003.com/",
            "origin": "https://executeandship.com"
        },
        {
            "name": "Ptv Sports Cricket",
            "url": "https://oz1.player0003.com:7061/hls/ptvskpr.m3u8?md5=E9JiD8dXyVhqAf2N3RdxiQ&expires=1781314955&ch=ptvskpr&s=b863b3c155e95392470ff29666c8f343",
            "referer": "https://player0003.com/",
            "origin": "https://player0003.com"
        },
        {
            "name": "NBC Sports Now",
            "url": "https://cdn2.zohanayaan.com:1686/hls/nbccs.m3u8?md5=vvksmvtpKbHyE9nx7Jifog&expires=1781314964",
            "referer": "https://executeandship.com/",
            "origin": "https://executeandship.com"
        },
        {
            "name": "TNT Sports 1",
            "url": "https://cdn1.zohanayaan.com:1686/hls/bbtsp1.m3u8?md5=e83Ugxcq6Hiyn5DSN7TwhQ&expires=1781314973",
            "referer": "https://executeandship.com/",
            "origin": "https://executeandship.com"
        },
        {
            "name": "TNT Sports",
            "url": "https://cdn7.zohanayaan.com:1686/hls/hdchnl2.m3u8?md5=pTzfr2Y0RZRCUtutQUFwQA&expires=1781314994",
            "referer": "https://executeandship.com/",
            "origin": "https://executeandship.com"
        },
        {
            "name": "Fox Sports 2",
            "url": "https://cdn2.zohanayaan.com:1686/hls/foxsp2usa.m3u8?md5=ldewU1qgaOYSPNGzUxvnLA&expires=1781315004",
            "referer": "https://executeandship.com/",
            "origin": "https://executeandship.com"
        },
        {
            "name": "Fox Deportes",
            "url": "https://cdn7.zohanayaan.com:1686/hls/foxdeportesas1.m3u8?md5=Y_Rz4VlO9EKTlCqS0Jz05w&expires=1781315014",
            "referer": "https://executeandship.com/",
            "origin": "https://executeandship.com"
        },
        {
            "name": "Sky Sports 2",
            "url": "https://cdn7.zohanayaan.com:1686/hls/sky2nz.m3u8?md5=pe_atP1uvxYkYHJa8baG0w&expires=1781315025",
            "referer": "https://executeandship.com/",
            "origin": "https://executeandship.com"
        },
        {
            "name": "Sky Sports Tennis",
            "url": "https://cdn9.zohanayaan.com:1686/hls/skystennis.m3u8?md5=B2ce6_X_yRTG06sJAbf7NA&expires=1781315033",
            "referer": "https://executeandship.com/",
            "origin": "https://executeandship.com"
        },
        {
            "name": "Espn Nba",
            "url": "https://cdn4.zohanayaan.com:1686/hls/espn2.m3u8?md5=k0wFqlVLH2GAAnCNpgJWUw&expires=1781315041",
            "referer": "https://executeandship.com/",
            "origin": "https://executeandship.com"
        },
        {
            "name": "A Sports",
            "url": "https://cdn5.zohanayaan.com:1686/hls/asportshd.m3u8?md5=pngWmpQB3qC8FIfDeVfxZA&expires=1781315052",
            "referer": "https://executeandship.com/",
            "origin": "https://executeandship.com"
        },
        {
            "name": "Ten Sports",
            "url": "https://cdn1.zohanayaan.com:1686/hls/tenspk.m3u8?md5=I3Lx115ehLS_LJhcXU3B6w&expires=1781315061",
            "referer": "https://executeandship.com/",
            "origin": "https://executeandship.com"
        },
        {
            "name": "BBC News",
            "url": "https://cdn5.zohanayaan.com:1686/hls/hdchnl1.m3u8?md5=XHx995R6t8QcrHVa-GLQ2A&expires=1781315071",
            "referer": "https://executeandship.com/",
            "origin": "https://executeandship.com"
        },
        {
            "name": "Star Sports 1",
            "url": "https://oz1.player0003.com:7061/hls/star1kibich5.m3u8?md5=J1xpRgMK0rRLkvicpKrluw&expires=1781315083&ch=star1kibich5&s=6b853d908f102ff4311e1913b7a8979e",
            "referer": "https://player0003.com/",
            "origin": "https://executeandship.com"
        },
        {
            "name": "willow HD",
            "url": "https://cdn8.zohanayaan.com:1686/hls/willowusa.m3u8?md5=tivdkWykyWuc9aJ57JUjAA&expires=1781315061",
            "referer": "https://executeandship.com/",
            "origin": "https://executeandship.com"
        },
        {
            "name": "ESPN Deportes",
            "url": "https://cdn9.zohanayaan.com:1686/hls/espndeportess.m3u8?md5=nrtGfIe4KtHdphWd8ru2aQ&expires=1781315101",
            "referer": "https://executeandship.com/",
            "origin": "https://executeandship.com"
        },
        {
            "name": "Fox Sports 1",
            "url": "https://cdn4.zohanayaan.com:1686/hls/foxsp1usa.m3u8?md5=N_mNBG1xSGgReb6tjSq9fA&expires=1781315112",
            "referer": "https://executeandship.com/",
            "origin": "https://executeandship.com"
        }
    ]
}